odoo9_addon_users_ldap_mail-9.0.1.0.0.99.dev14-py2.7-nspkg.pth
odoo9_addon_users_ldap_mail-9.0.1.0.0.99.dev14.dist-info/DESCRIPTION.rst
odoo9_addon_users_ldap_mail-9.0.1.0.0.99.dev14.dist-info/METADATA
odoo9_addon_users_ldap_mail-9.0.1.0.0.99.dev14.dist-info/RECORD
odoo9_addon_users_ldap_mail-9.0.1.0.0.99.dev14.dist-info/WHEEL
odoo9_addon_users_ldap_mail-9.0.1.0.0.99.dev14.dist-info/metadata.json
odoo9_addon_users_ldap_mail-9.0.1.0.0.99.dev14.dist-info/namespace_packages.txt
odoo9_addon_users_ldap_mail-9.0.1.0.0.99.dev14.dist-info/top_level.txt
odoo_addons/users_ldap_mail/__init__.py
odoo_addons/users_ldap_mail/__openerp__.py
odoo_addons/users_ldap_mail/users_ldap_model.py
odoo_addons/users_ldap_mail/users_ldap_view.xml
odoo_addons/users_ldap_mail/i18n/ca.po
odoo_addons/users_ldap_mail/i18n/de.po
odoo_addons/users_ldap_mail/i18n/es.po
odoo_addons/users_ldap_mail/i18n/fr.po
odoo_addons/users_ldap_mail/i18n/hr.po
odoo_addons/users_ldap_mail/i18n/hr_HR.po
odoo_addons/users_ldap_mail/i18n/pt_BR.po
odoo_addons/users_ldap_mail/i18n/sl.po
odoo_addons/users_ldap_mail/i18n/tr.po
odoo_addons/users_ldap_mail/i18n/users_ldap_mail.pot
odoo_addons/users_ldap_mail/i18n/zh_CN.po
odoo_addons/users_ldap_mail/static/description/icon.png
